assemblypy/__init__.py
assemblypy/ssembly.py
assemblypy-0.1.1.dist-info/licenses/license
assemblypy-0.1.1.dist-info/METADATA
assemblypy-0.1.1.dist-info/WHEEL
assemblypy-0.1.1.dist-info/top_level.txt
assemblypy-0.1.1.dist-info/RECORD
